Metadata-Version: 1.1
Name: pngify
Version: 0.4
Summary: Inject and extract data from PNG files
Home-page: https://github.com/moertle/pngify
Author: Matthew Oertle
Author-email: moertle@gmail.com
License: MIT
Platform: UNKNOWN
Classifier: Development Status :: 4 - Beta
Classifier: Environment :: Console
Classifier: License :: OSI Approved :: MIT License
Classifier: Topic :: Software Development :: Libraries
Classifier: Programming Language :: Python :: 2.7
Classifier: Programming Language :: Python :: 3
